PtpUploader/Helper.py
PtpUploader/ImageHost/Base.py
PtpUploader/ImageHost/Catbox.py
PtpUploader/ImageHost/ImageUploader.py
PtpUploader/ImageHost/ImgBB.py
PtpUploader/ImageHost/PtpImg.py
PtpUploader/ImageHost/__init__.py
PtpUploader/IncludedFileList.py
PtpUploader/InformationSource/Imdb.py
PtpUploader/InformationSource/MoviePoster.py
PtpUploader/InformationSource/__init__.py
PtpUploader/Job/CheckAnnouncement.py
PtpUploader/Job/Delete.py
PtpUploader/Job/FinishedJobPhase.py
PtpUploader/Job/JobRunningState.py
PtpUploader/Job/JobStartMode.py
PtpUploader/Job/LoadFile.py
PtpUploader/Job/Supervisor.py
PtpUploader/Job/Upload.py
PtpUploader/Job/WorkerBase.py
PtpUploader/Job/__init__.py
PtpUploader/MyGlobals.py
PtpUploader/Notifier.example.ini
PtpUploader/Notifier.py
PtpUploader/Ptp.py
PtpUploader/PtpImdbInfo.py
PtpUploader/PtpMovieSearchResult.py
PtpUploader/PtpUploaderException.py
PtpUploader/PtpUploaderMessage.py
PtpUploader/ReleaseDescriptionFormatter.py
PtpUploader/ReleaseInfo.py
PtpUploader/ReleaseInfoMaker.py
PtpUploader/ReleaseNameParser.py
PtpUploader/SceneGroups.txt
PtpUploader/Settings.py
PtpUploader/Source/Cinemageddon.py
PtpUploader/Source/File.py
PtpUploader/Source/Karagarga.py
PtpUploader/Source/Prowlarr.py
PtpUploader/Source/SourceBase.py
PtpUploader/Source/SourceFactory.py
PtpUploader/Source/Torrent.py
PtpUploader/Source/__init__.py
PtpUploader/Tool/BdInfo.py
PtpUploader/Tool/Ffmpeg.py
PtpUploader/Tool/ImageMagick.py
PtpUploader/Tool/LibMpv.py
PtpUploader/Tool/MediaInfo.py
PtpUploader/Tool/Mktor.py
PtpUploader/Tool/Mplayer.py
PtpUploader/Tool/Mpv.py
PtpUploader/Tool/Oxipng.py
PtpUploader/Tool/Rtorrent.py
PtpUploader/Tool/ScreenshotMaker.py
PtpUploader/Tool/Transmission.py
PtpUploader/Tool/Unrar.py
PtpUploader/Tool/__init__.py
PtpUploader/__init__.py
PtpUploader/config.default.yml
PtpUploader/included_file_list.py
PtpUploader/manage.py
PtpUploader/nfo_parser.py
PtpUploader/ptp_subtitle.py
PtpUploader/release_extractor.py
PtpUploader/web/__init__.py
ptpuploader-0.12.2.dist-info/METADATA
ptpuploader-0.12.2.dist-info/WHEEL
ptpuploader-0.12.2.dist-info/entry_points.txt
ptpuploader-0.12.2.dist-info/RECORD
