Metadata-Version: 2.1
Name: PtpUploader
Version: 0.12.2
Summary: A small uploader for a mildly popular movie site
Home-page: https://github.com/kannibalox/PtpUploader
Author: kannibalox
Author-email: kannibalox@gmail.com
Requires-Python: >3.7.2,<4.0
Classifier: Development Status :: 4 - Beta
Classifier: Environment :: Web Environment
Classifier: Natural Language :: English
Classifier: Operating System :: POSIX
Classifier: Programming Language :: Python :: 3
Classifier: Programming Language :: Python :: 3.8
Classifier: Programming Language :: Python :: 3.9
Classifier: Programming Language :: Python :: 3.10
Classifier: Programming Language :: Python :: 3.11
Classifier: Programming Language :: Python :: 3 :: Only
Classifier: Programming Language :: Python :: 3.7
Classifier: Topic :: Utilities
Requires-Dist: Django (>=3.2.19,<4.0.0)
Requires-Dist: Unidecode (>=1.3.2,<2.0.0)
Requires-Dist: Werkzeug (>=2.0.2,<3.0.0)
Requires-Dist: cinemagoer (>=2023.5.1,<2024.0.0)
Requires-Dist: dynaconf (>=3.1.7,<4.0.0)
Requires-Dist: guessit (>=3.3.1,<4.0.0)
Requires-Dist: pyrosimple (>=2.7.0,<3.0.0)
Requires-Dist: rarfile (>=4.0,<5.0)
Requires-Dist: requests (>=2.26.0,<3.0.0)
Project-URL: Repository, https://github.com/kannibalox/PtpUploader
